image_registration/__init__.py
image_registration/_astropy_init.py
image_registration/chi2_shifts.py
image_registration/conftest.py
image_registration/cross_correlation_shifts.py
image_registration/iterative_zoom.py
image_registration/register_images.py
image_registration/version.py
image_registration/FITS_tools/__init__.py
image_registration/FITS_tools/fits_overlap.py
image_registration/FITS_tools/hcongrid.py
image_registration/FITS_tools/load_header.py
image_registration/FITS_tools/match_images.py
image_registration/fft_tools/__init__.py
image_registration/fft_tools/convolve_nd.py
image_registration/fft_tools/correlate2d.py
image_registration/fft_tools/downsample.py
image_registration/fft_tools/fast_ffts.py
image_registration/fft_tools/scale.py
image_registration/fft_tools/shift.py
image_registration/fft_tools/smooth_tools.py
image_registration/fft_tools/upsample.py
image_registration/fft_tools/zoom.py
image_registration/fft_tools/tests/__init__.py
image_registration/fft_tools/tests/measure_accuracy.py
image_registration/fft_tools/tests/test_downsample.py
image_registration/fft_tools/tests/test_shift.py
image_registration/fft_tools/tests/test_upsample.py
image_registration/fft_tools/tests/test_upsample_1d.py
image_registration/fft_tools/tests/test_zoomnd.py
image_registration/tests/__init__.py
image_registration/tests/debug_test.py
image_registration/tests/measure_expected_offsets.py
image_registration/tests/registration_testing.py
image_registration/tests/setup_package.py
image_registration/tests/tests.py
image_registration-0.2.9.dist-info/LICENSE
image_registration-0.2.9.dist-info/METADATA
image_registration-0.2.9.dist-info/WHEEL
image_registration-0.2.9.dist-info/entry_points.txt
image_registration-0.2.9.dist-info/top_level.txt
image_registration-0.2.9.dist-info/RECORD
