Metadata-Version: 2.1
Name: image_registration
Version: 0.2.9
Summary: Package for registering images with extended emission
Home-page: https://image-registration.readthedocs.io/en/latest/
Author: Adam Ginsburg
Author-email: adam.g.ginsburg@gmail.com
License: BSD
Requires-Python: >=3.7
License-File: LICENSE
Requires-Dist: astropy
Requires-Dist: matplotlib
Requires-Dist: pytest
Provides-Extra: docs
Requires-Dist: sphinx-astropy ; extra == 'docs'
Requires-Dist: matplotlib ; extra == 'docs'
Requires-Dist: FITS-tools ; extra == 'docs'
Requires-Dist: astropy ; extra == 'docs'
Requires-Dist: scipy ; extra == 'docs'
Provides-Extra: test
Requires-Dist: pytest-astropy ; extra == 'test'
Requires-Dist: matplotlib ; extra == 'test'
